README.rst
setup.py
stringexchange/__init__.py
stringexchange/compat.py
stringexchange/interfaces.py
stringexchange.egg-info/PKG-INFO
stringexchange.egg-info/SOURCES.txt
stringexchange.egg-info/dependency_links.txt
stringexchange.egg-info/entry_points.txt
stringexchange.egg-info/not-zip-safe
stringexchange.egg-info/requires.txt
stringexchange.egg-info/top_level.txt
stringexchange/tests/__init__.py
stringexchange/tests/test_emitter.py
stringexchange/tests/test_it.py